{
  "trial_id": 349,
  "params": {
    "MODEL_TYPE": "lgbm",
    "model_n_estimators": 200,
    "model_max_depth": 3,
    "model_learning_rate": 0.054657822168375066,
    "model_subsample": 0.7884105108132458,
    "model_colsample": 0.6212627251766869,
    "xgb_min_child_weight": 2,
    "lgbm_num_leaves": 63,
    "lgbm_min_child_samples": 41,
    "FDR_MULT": 0.0257879888958052,
    "FDR_MULT_DEF": 0.0882728662998357,
    "BENCH_BONUS_NORMAL": 2.80981616201246,
    "BENCH_BONUS_BB_GW": 5.710644701991433,
    "CAP_FORM_GATE": 2.736422121054412,
    "CAP_FORM_PENALTY": 0.2527359207305544,
    "OWN_BOOST_GW1": 0.14605760392616546,
    "CAP_STREAK_LIMIT": 2,
    "CAP_STREAK_MULT": 0.8896025711244497,
    "TC_THRESH": 5.631925003614419,
    "BB_MIN_GW": 8,
    "CAP_FDR_MULT": 0.022668724756615556,
    "CAP_BLANK_PENALTY": 0.7938652177314903,
    "CAP_BLANK_THRESH": 4
  },
  "total": 1741,
  "penalties": -8,
  "chips": [
    "tc1",
    "bb1",
    "wc1",
    "tc2",
    "bb2",
    "fh2"
  ],
  "elapsed": 65,
  "status": "ok",
  "gw_scores": [
    {
      "gw": 1,
      "actual": 85,
      "chip": null
    },
    {
      "gw": 2,
      "actual": 59,
      "chip": null
    },
    {
      "gw": 3,
      "actual": 71,
      "chip": null
    },
    {
      "gw": 4,
      "actual": 79,
      "chip": null
    },
    {
      "gw": 5,
      "actual": 63,
      "chip": null
    },
    {
      "gw": 6,
      "actual": 104,
      "chip": "tc1"
    },
    {
      "gw": 7,
      "actual": 64,
      "chip": null
    },
    {
      "gw": 8,
      "actual": 87,
      "chip": "bb1"
    },
    {
      "gw": 9,
      "actual": 42,
      "chip": null
    },
    {
      "gw": 10,
      "actual": 80,
      "chip": null
    },
    {
      "gw": 11,
      "actual": 39,
      "chip": null
    },
    {
      "gw": 12,
      "actual": 43,
      "chip": null
    },
    {
      "gw": 13,
      "actual": 45,
      "chip": null
    },
    {
      "gw": 14,
      "actual": 79,
      "chip": null
    },
    {
      "gw": 15,
      "actual": 51,
      "chip": null
    },
    {
      "gw": 16,
      "actual": 77,
      "chip": null
    },
    {
      "gw": 17,
      "actual": 71,
      "chip": "wc1"
    },
    {
      "gw": 18,
      "actual": 35,
      "chip": null
    },
    {
      "gw": 19,
      "actual": 37,
      "chip": null
    },
    {
      "gw": 20,
      "actual": 46,
      "chip": "tc2"
    },
    {
      "gw": 21,
      "actual": 76,
      "chip": null
    },
    {
      "gw": 22,
      "actual": 40,
      "chip": null
    },
    {
      "gw": 23,
      "actual": 63,
      "chip": "bb2"
    },
    {
      "gw": 24,
      "actual": 54,
      "chip": null
    },
    {
      "gw": 25,
      "actual": 75,
      "chip": null
    },
    {
      "gw": 26,
      "actual": 55,
      "chip": "fh2"
    },
    {
      "gw": 27,
      "actual": 46,
      "chip": null
    },
    {
      "gw": 28,
      "actual": 75,
      "chip": null
    }
  ]
}