{
  "trial_id": 98,
  "params": {
    "MODEL_TYPE": "lgbm",
    "model_n_estimators": 100,
    "model_max_depth": 3,
    "model_learning_rate": 0.0430026272924601,
    "model_subsample": 0.9491024539645629,
    "model_colsample": 0.6517068492072363,
    "xgb_min_child_weight": 4,
    "lgbm_num_leaves": 31,
    "lgbm_min_child_samples": 49,
    "FDR_MULT": 0.025070678588757406,
    "FDR_MULT_DEF": 0.09027235656078106,
    "BENCH_BONUS_NORMAL": 2.88762228760626,
    "BENCH_BONUS_BB_GW": 3.1178841638524224,
    "CAP_FORM_GATE": 2.65120118279612,
    "CAP_FORM_PENALTY": 0.38172851445265166,
    "OWN_BOOST_GW1": 0.20596717862040856,
    "CAP_STREAK_LIMIT": 5,
    "CAP_STREAK_MULT": 0.8617597450927434,
    "TC_THRESH": 6.435810853203751,
    "BB_MIN_GW": 8,
    "CAP_FDR_MULT": 0.008470199013263555,
    "CAP_BLANK_PENALTY": 0.8103467689197538,
    "CAP_BLANK_THRESH": 4
  },
  "total": 1741,
  "penalties": 0,
  "chips": [
    "tc1",
    "bb1",
    "wc1",
    "tc2",
    "bb2",
    "fh2"
  ],
  "elapsed": 62,
  "status": "ok",
  "gw_scores": [
    {
      "gw": 1,
      "actual": 82,
      "chip": null
    },
    {
      "gw": 2,
      "actual": 76,
      "chip": null
    },
    {
      "gw": 3,
      "actual": 75,
      "chip": null
    },
    {
      "gw": 4,
      "actual": 100,
      "chip": null
    },
    {
      "gw": 5,
      "actual": 54,
      "chip": null
    },
    {
      "gw": 6,
      "actual": 102,
      "chip": "tc1"
    },
    {
      "gw": 7,
      "actual": 65,
      "chip": null
    },
    {
      "gw": 8,
      "actual": 80,
      "chip": "bb1"
    },
    {
      "gw": 9,
      "actual": 47,
      "chip": null
    },
    {
      "gw": 10,
      "actual": 84,
      "chip": null
    },
    {
      "gw": 11,
      "actual": 42,
      "chip": null
    },
    {
      "gw": 12,
      "actual": 37,
      "chip": null
    },
    {
      "gw": 13,
      "actual": 42,
      "chip": null
    },
    {
      "gw": 14,
      "actual": 58,
      "chip": null
    },
    {
      "gw": 15,
      "actual": 72,
      "chip": null
    },
    {
      "gw": 16,
      "actual": 61,
      "chip": null
    },
    {
      "gw": 17,
      "actual": 56,
      "chip": "wc1"
    },
    {
      "gw": 18,
      "actual": 39,
      "chip": null
    },
    {
      "gw": 19,
      "actual": 41,
      "chip": null
    },
    {
      "gw": 20,
      "actual": 36,
      "chip": "tc2"
    },
    {
      "gw": 21,
      "actual": 91,
      "chip": null
    },
    {
      "gw": 22,
      "actual": 38,
      "chip": null
    },
    {
      "gw": 23,
      "actual": 48,
      "chip": "bb2"
    },
    {
      "gw": 24,
      "actual": 56,
      "chip": null
    },
    {
      "gw": 25,
      "actual": 64,
      "chip": null
    },
    {
      "gw": 26,
      "actual": 69,
      "chip": "fh2"
    },
    {
      "gw": 27,
      "actual": 51,
      "chip": null
    },
    {
      "gw": 28,
      "actual": 75,
      "chip": null
    }
  ]
}